{
  "use_cache": true,
  "metadata": {
    "micron": 0.1565932,
    "micron_radius": 1,
    "is_spreading": false
  },
  "mask_radius": {
    "small_radius": 15,
    "large_radius": 35
  },
  "outer_inner_intensity_ratio": 1.2,
  "percentage_from_perfect_circle_mask": 1,
  "experiment": {
    "id": "20230323-06-4",
    "tif_path": "\\exp-20230323-video-06-cell-4-Airyscan Processing-04-driftC.tif"
  },
  "tagged_centers": ["(34, 142)","(49, 161)","(66, 176)","(89, 176)","(73, 157)","(57, 138)","(41, 119)","(25, 100)","(34, 76)","(21, 123)","(76, 25)","(101, 20)","(127, 19)","(117, 38)","(92, 43)","(67, 47)","(42, 52)","(59, 71)","(50, 95)","(66, 114)","(82, 134)","(98, 153)","(123, 148)","(148, 144)","(132, 125)","(116, 106)","(99, 86)","(91, 110)","(108, 62)","(133, 58)","(141, 34)","(158, 54)","(174, 73)","(165, 97)","(149, 77)","(157, 119)","(171, 139)","(138, 165)","(114, 170)","(141, 101)","(125, 81)","(188, 91)","(180, 115)","(194, 68)","(183, 50)","(165, 32)","(84, 67)","(75, 91)","(55, 33)","(107, 129)"],
  "perturbation": {
    "type": "5.3"
  },
  "pixel_to_whiten": 50,
  "output_path_type": "5_3",
  "normalized": false,
  "fixed": true,
  "operations": [
    {
      "show_pillars_mask": {}
    },
    {
      "avg_intensity": {}
    },
    {
      "neighbors_avg_correlation": {}
    },
    {
      "non_neighbors_avg_correlation": {}
    },
    {
      "_correlation_plot": {
        "only_alive": true,
        "neighbors": "all",
        "alive_correlation_type": "symmetric"
      }
    },
    {
      "neighbors_correlation_histogram": {
        "neighbors": "real_neighbors"
      }
    },
    {
      "non_neighbors_correlation_histogram": {}
    },
    {
      "correlation_histogram": {
        "alive": true
      }
    },
    {
      "_show_correlated_pairs_in_video": {
        "num_of_pairs": 5
      }
    },
    {
      "_plot_pillar_pairs_correlation_frames_window": {
        "num_of_pairs": 5
      }
    },
    {
      "_show_correlated_neighboring_pairs_in_video": {
        "num_of_pairs": 5
      }
    },
    {
      "_plot_neighboring_pillar_pairs_correlation_frames_window": {
        "num_of_pairs": 5
      }
    },
    {
      "_show_neighboring_correlated_pairs_in_last_image": {
        "num_of_pairs": 5
      }
    },
    {
      "_number_of_neighboring_pairs_in_top_correlations": {
        "top": 10
      }
    },
    {
      "_compare_neighbors_corr_histogram_random_vs_real": {
        "random_amount": 5
      }
    },
    {
      "_gc_graph": {}
    },
    {
      "_edges_distribution_plots": {}
    },
    {
      "_in_out_gc_edges": {}
    },
    {
      "_gc_edge_prob": {}
    },
    {
      "_gc_edge_prob_original_vs_random": {}
    },
    {
      "_in_out_degree": {}
    },
    {
      "_reciprocity": {}
    },
    {
      "_heterogeneity": {}
    },
    {
      "_neighbors_avg_movement_correlation": {}
    },
    {
      "_not_neighbors_avg_movement_correlation": {}
    },
    {
      "change_mask_radius": {}
    }
  ]
}
